setup.cfg
setup.py
yqmd/__init__.py
yqmd/yqmd.py
yqmd.egg-info/PKG-INFO
yqmd.egg-info/SOURCES.txt
yqmd.egg-info/dependency_links.txt
yqmd.egg-info/top_level.txt