Metadata-Version: 1.1
Name: yqmd
Version: 0.1.2
Summary: Utility lib for working with common period types
Home-page: https://github.com/vibze/yqmd.py
Author: Viktor Ten
Author-email: ten.viktor@gmail.com
License: UNKNOWN
Download-URL: https://github.com/vibze/yqmd.py/archive/0.1.1.tar.gz
Keywords: date
Platform: UNKNOWN
